yuumi/__init__.py
yuumi/cli.py
yuumi/debrid/__init__.py
yuumi/debrid/real_debrid.py
yuumi/requests.py
yuumi-0.3.2.dist-info/METADATA
yuumi-0.3.2.dist-info/WHEEL
yuumi-0.3.2.dist-info/entry_points.txt
yuumi-0.3.2.dist-info/RECORD
