Metadata-Version: 2.1
Name: yuumi
Version: 0.3.2
Summary: Debrid Manager Python package
Author: Dreu LaVelle
Author-email: dreu.lavelle@gmail.com
Requires-Python: >=3.11,<4.0
Classifier: Programming Language :: Python :: 3
Classifier: Programming Language :: Python :: 3.11
Classifier: Programming Language :: Python :: 3.12
Requires-Dist: requests (>=2.32.3,<3.0.0)
